I40Client/__init__.py
I40Client/__main__.py
I40Client/configuration.py
I40Client/encryption.py
I40Client/server_connection.py
I40Client/Utilities/__init__.py
I40Client/Utilities/chatbot_tools.py
I40Client/Utilities/format_conversion.py
I40Client/Utilities/internet.py
i4_0_client_py-17.0.0.dist-info/METADATA
i4_0_client_py-17.0.0.dist-info/WHEEL
i4_0_client_py-17.0.0.dist-info/entry_points.txt
i4_0_client_py-17.0.0.dist-info/top_level.txt
i4_0_client_py-17.0.0.dist-info/RECORD
