Metadata-Version: 2.4
Name: I4_0-Client-PY
Version: 17.0.0
Summary: Python bindings for I4.0, Client-side.
Author: TAO71-AI
License: TAO71 I4.0 License (version 2)
Project-URL: Homepage, https://github.com/TAO71-AI/I4.0-NEW
Project-URL: Source, https://github.com/TAO71-AI/I4.0-NEW/tree/master/Client
Project-URL: License, https://github.com/TAO71-AI/I4.0-NEW/blob/master/LICENSE.md
Classifier: Programming Language :: Python :: 3
Classifier: License :: Other/Proprietary License
Classifier: Operating System :: OS Independent
Requires-Python: >=3.11
Requires-Dist: websockets<16.0.0,>=15.0.0
Requires-Dist: asyncio
Requires-Dist: cryptography
Requires-Dist: html2text
